{
  "words": [
    {"word": "cat", "difficulty": 1, "phonics": ["CVC", "short-a"], "theme": "animals", "syllables": 1},
    {"word": "bat", "difficulty": 1, "phonics": ["CVC", "short-a"], "theme": "animals", "syllables": 1},
    {"word": "hat", "difficulty": 1, "phonics": ["CVC", "short-a"], "theme": "clothing", "syllables": 1},
    {"word": "mat", "difficulty": 1, "phonics": ["CVC", "short-a"], "theme": "home", "syllables": 1},
    {"word": "dog", "difficulty": 1, "phonics": ["CVC", "short-o"], "theme": "animals", "syllables": 1},
    {"word": "log", "difficulty": 1, "phonics": ["CVC", "short-o"], "theme": "nature", "syllables": 1},
    {"word": "pig", "difficulty": 1, "phonics": ["CVC", "short-i"], "theme": "animals", "syllables": 1},
    {"word": "big", "difficulty": 1, "phonics": ["CVC", "short-i"], "theme": "descriptive", "syllables": 1},
    {"word": "sun", "difficulty": 1, "phonics": ["CVC", "short-u"], "theme": "nature", "syllables": 1},
    {"word": "run", "difficulty": 1, "phonics": ["CVC", "short-u"], "theme": "actions", "syllables": 1},
    {"word": "bed", "difficulty": 1, "phonics": ["CVC", "short-e"], "theme": "home", "syllables": 1},
    {"word": "red", "difficulty": 1, "phonics": ["CVC", "short-e"], "theme": "colors", "syllables": 1},
    {"word": "frog", "difficulty": 2, "phonics": ["CCVC", "blend-fr"], "theme": "animals", "syllables": 1},
    {"word": "flag", "difficulty": 2, "phonics": ["CCVC", "blend-fl"], "theme": "objects", "syllables": 1},
    {"word": "clap", "difficulty": 2, "phonics": ["CCVC", "blend-cl"], "theme": "actions", "syllables": 1},
    {"word": "drip", "difficulty": 2, "phonics": ["CCVC", "blend-dr"], "theme": "nature", "syllables": 1},
    {"word": "ship", "difficulty": 2, "phonics": ["CVCC", "digraph-sh"], "theme": "transport", "syllables": 1},
    {"word": "chip", "difficulty": 2, "phonics": ["CVCC", "digraph-ch"], "theme": "food", "syllables": 1},
    {"word": "thin", "difficulty": 2, "phonics": ["CVCC", "digraph-th"], "theme": "descriptive", "syllables": 1},
    {"word": "when", "difficulty": 2, "phonics": ["CVCC", "digraph-wh"], "theme": "question", "syllables": 1},
    {"word": "jump", "difficulty": 2, "phonics": ["CVCC", "blend-mp"], "theme": "actions", "syllables": 1},
    {"word": "lamp", "difficulty": 2, "phonics": ["CVCC", "blend-mp"], "theme": "home", "syllables": 1},
    {"word": "rain", "difficulty": 3, "phonics": ["vowel-team-ai"], "theme": "nature", "syllables": 1},
    {"word": "boat", "difficulty": 3, "phonics": ["vowel-team-oa"], "theme": "transport", "syllables": 1},
    {"word": "feet", "difficulty": 3, "phonics": ["vowel-team-ee"], "theme": "body", "syllables": 1},
    {"word": "seed", "difficulty": 3, "phonics": ["vowel-team-ee"], "theme": "nature", "syllables": 1},
    {"word": "night", "difficulty": 3, "phonics": ["silent-gh", "igh"], "theme": "time", "syllables": 1},
    {"word": "light", "difficulty": 3, "phonics": ["silent-gh", "igh"], "theme": "objects", "syllables": 1},
    {"word": "cake", "difficulty": 3, "phonics": ["CVCe", "long-a"], "theme": "food", "syllables": 1},
    {"word": "bike", "difficulty": 3, "phonics": ["CVCe", "long-i"], "theme": "transport", "syllables": 1},
    {"word": "home", "difficulty": 3, "phonics": ["CVCe", "long-o"], "theme": "home", "syllables": 1},
    {"word": "cube", "difficulty": 3, "phonics": ["CVCe", "long-u"], "theme": "shapes", "syllables": 1},
    {"word": "happy", "difficulty": 4, "phonics": ["multisyllabic", "short-a", "short-e"], "theme": "emotions", "syllables": 2},
    {"word": "funny", "difficulty": 4, "phonics": ["multisyllabic", "short-u"], "theme": "descriptive", "syllables": 2},
    {"word": "rabbit", "difficulty": 4, "phonics": ["multisyllabic", "double-consonant"], "theme": "animals", "syllables": 2},
    {"word": "kitten", "difficulty": 4, "phonics": ["multisyllabic", "double-consonant"], "theme": "animals", "syllables": 2},
    {"word": "garden", "difficulty": 4, "phonics": ["multisyllabic", "r-controlled"], "theme": "nature", "syllables": 2},
    {"word": "butter", "difficulty": 4, "phonics": ["multisyllabic", "r-controlled"], "theme": "food", "syllables": 2},
    {"word": "elephant", "difficulty": 5, "phonics": ["multisyllabic", "blend-el"], "theme": "animals", "syllables": 3},
    {"word": "umbrella", "difficulty": 5, "phonics": ["multisyllabic", "short-u"], "theme": "objects", "syllables": 3},
    {"word": "butterfly", "difficulty": 5, "phonics": ["multisyllabic", "blend-fl"], "theme": "animals", "syllables": 3},
    {"word": "adventure", "difficulty": 5, "phonics": ["multisyllabic", "r-controlled"], "theme": "actions", "syllables": 3},
    {"word": "beautiful", "difficulty": 5, "phonics": ["multisyllabic", "vowel-team-eau"], "theme": "descriptive", "syllables": 4},
    {"word": "important", "difficulty": 5, "phonics": ["multisyllabic", "r-controlled"], "theme": "descriptive", "syllables": 3}
  ],
  "themes": ["animals", "food", "nature", "home", "colors", "actions", "transport", "body", "clothing", "emotions", "descriptive", "objects", "shapes", "time", "question"],
  "difficulty_labels": {
    "1": "Beginner (CVC)",
    "2": "Elementary (Blends & Digraphs)",
    "3": "Intermediate (Vowel Teams & Silent Letters)",
    "4": "Advanced (Multisyllabic)",
    "5": "Expert (Complex Words)"
  }
}
